alidaparse/__init__.py
alidaparse/core.py
alidaparse/input/InDataset.py
alidaparse/input/InModel.py
alidaparse/input/InParam.py
alidaparse/input/__init__.py
alidaparse/message_broker/__init__.py
alidaparse/message_broker/message_broker.py
alidaparse/message_broker/utils.py
alidaparse/output/OutDataset.py
alidaparse/output/OutModel.py
alidaparse/output/__init__.py
alidaparse/utils/__init__.py
alidaparse/utils/minio.py
alidaparse/utils/progress.py
alidaparse-0.2.5.dist-info/licenses/LICENSE
alidaparse-0.2.5.dist-info/METADATA
alidaparse-0.2.5.dist-info/WHEEL
alidaparse-0.2.5.dist-info/top_level.txt
alidaparse-0.2.5.dist-info/RECORD
