Metadata-Version: 2.4
Name: alidaparse
Version: 0.2.5
Summary: A parsing module for ALIDA's services
Requires-Python: >=3.10
License-File: LICENSE
Requires-Dist: gdown>=5.2.0
Requires-Dist: kafka-python>=2.2.15
Requires-Dist: minio>=7.2.16
Requires-Dist: pytest>=8.4.2
Dynamic: license-file
